zapdos/__init__.py
zapdos-0.1.0.dist-info/WHEEL
zapdos-0.1.0.dist-info/METADATA
zapdos-0.1.0.dist-info/RECORD
