Metadata-Version: 2.1
Name: zapdos
Version: 0.1.0
Summary: 
Author: Joseph Chu
Author-email: josephchu21@gmail.com
Requires-Python: >=3.11,<4.0
Classifier: Programming Language :: Python :: 3
Classifier: Programming Language :: Python :: 3.11
Requires-Dist: sphinx (>=5.3.0,<6.0.0)
